libddog/__init__.py
libddog/py.typed
libddog/__pycache__/__init__.cpython-38.pyc
libddog/command_line/__init__.py
libddog/command_line/console.py
libddog/command_line/dashboards.py
libddog/command_line/monitors.py
libddog/command_line/options.py
libddog/command_line/upgrade_check.py
libddog/common/__init__.py
libddog/common/bases.py
libddog/common/errors.py
libddog/common/types.py
libddog/crud/__init__.py
libddog/crud/client.py
libddog/crud/dashboards.py
libddog/crud/errors.py
libddog/crud/monitors.py
libddog/crud/users.py
libddog/dashboards/__init__.py
libddog/dashboards/components.py
libddog/dashboards/dashboards.py
libddog/dashboards/enums.py
libddog/dashboards/exceptions.py
libddog/dashboards/layouts.py
libddog/dashboards/presets.py
libddog/dashboards/widgets.py
libddog/metrics/__init__.py
libddog/metrics/bases.py
libddog/metrics/exceptions.py
libddog/metrics/formulas.py
libddog/metrics/functions.py
libddog/metrics/literals.py
libddog/metrics/query.py
libddog/metrics/support.py
libddog/metrics/__pycache__/__init__.cpython-38.pyc
libddog/metrics/__pycache__/exceptions.cpython-38.pyc
libddog/monitors/__init__.py
libddog/monitors/bases.py
libddog/monitors/components.py
libddog/monitors/enums.py
libddog/monitors/event_v2_alert_query.py
libddog/monitors/exceptions.py
libddog/monitors/metric_alert_query.py
libddog/monitors/monitors.py
libddog/parsing/__init__.py
libddog/parsing/extract_queries.py
libddog/parsing/extract_tmpl_vars.py
libddog/parsing/grammar.txt
libddog/parsing/parse_formula.py
libddog/parsing/query_parser.py
libddog/parsing/query_visitor.py
libddog/tools/__init__.py
libddog/tools/git.py
libddog/tools/logs.py
libddog/tools/process.py
libddog/tools/text.py
libddog/tools/timekeeping.py
libddog-0.1.8.post1.data/scripts/ddog
libddog-0.1.8.post1.dist-info/LICENSE
libddog-0.1.8.post1.dist-info/METADATA
libddog-0.1.8.post1.dist-info/WHEEL
libddog-0.1.8.post1.dist-info/top_level.txt
libddog-0.1.8.post1.dist-info/RECORD
